Metadata-Version: 1.0
Name: businessoptics-nb-ext
Version: 0.1
Summary: BusinessOptics IPython notebook extensions
Home-page: http://github.com/BusinessOptics/businessoptics_nb_ext
Author: James Saunders
Author-email: james@businessoptics.biz
License: MIT
Platform: UNKNOWN
